[
  {
    "sys": {
      "space": {
        "sys": {
          "type": "Link",
          "linkType": "Space",
          "id": "xanbi6q061ft"
        }
      },
      "id": "xtqahQbKA5kCvMoNBvDgr",
      "type": "Entry",
      "createdAt": "2021-03-04T08:11:34.685Z",
      "updatedAt": "2021-03-04T08:11:34.685Z",
      "environment": {
        "sys": {
          "id": "stg",
          "type": "Link",
          "linkType": "Environment"
        }
      },
      "revision": 1,
      "contentType": {
        "sys": {
          "type": "Link",
          "linkType": "ContentType",
          "id": "menuItem"
        }
      },
      "locale": "en-US"
    },
    "fields": {
      "title": "Women",
      "menuItemCategories": [
        {
          "sys": {
            "space": {
              "sys": {
                "type": "Link",
                "linkType": "Space",
                "id": "xanbi6q061ft"
              }
            },
            "id": "1YCYW6bPLACSkl8VnSiRLv",
            "type": "Entry",
            "createdAt": "2021-03-04T08:05:04.731Z",
            "updatedAt": "2021-03-04T08:05:04.731Z",
            "environment": {
              "sys": {
                "id": "stg",
                "type": "Link",
                "linkType": "Environment"
              }
            },
            "revision": 1,
            "contentType": {
              "sys": {
                "type": "Link",
                "linkType": "ContentType",
                "id": "menuItemCategory"
              }
            },
            "locale": "en-US"
          },
          "fields": {
            "title": "Shoes",
            "subCategories": [
              {
                "sys": {
                  "space": {
                    "sys": {
                      "type": "Link",
                      "linkType": "Space",
                      "id": "xanbi6q061ft"
                    }
                  },
                  "id": "1QrzJF7HyurLyWTROz9LCp",
                  "type": "Entry",
                  "createdAt": "2021-03-04T08:01:59.458Z",
                  "updatedAt": "2021-03-04T08:01:59.458Z",
                  "environment": {
                    "sys": {
                      "id": "stg",
                      "type": "Link",
                      "linkType": "Environment"
                    }
                  },
                  "revision": 1,
                  "contentType": {
                    "sys": {
                      "type": "Link",
                      "linkType": "ContentType",
                      "id": "menuItemSubCategory"
                    }
                  },
                  "locale": "en-US"
                },
                "fields": {
                  "title": "Running Shoes",
                  "subCategoryLinks": [
                    {
                      "sys": {
                        "space": {
                          "sys": {
                            "type": "Link",
                            "linkType": "Space",
                            "id": "xanbi6q061ft"
                          }
                        },
                        "id": "1VADNshfiQH4BnmIHnJ2YR",
                        "type": "Entry",
                        "createdAt": "2021-03-04T08:01:21.070Z",
                        "updatedAt": "2021-03-04T08:01:21.070Z",
                        "environment": {
                          "sys": {
                            "id": "stg",
                            "type": "Link",
                            "linkType": "Environment"
                          }
                        },
                        "revision": 1,
                        "contentType": {
                          "sys": {
                            "type": "Link",
                            "linkType": "ContentType",
                            "id": "navigationLink"
                          }
                        },
                        "locale": "en-US"
                      },
                      "fields": {
                        "title": "Wide",
                        "url": "/wide"
                      }
                    },
                    {
                      "sys": {
                        "space": {
                          "sys": {
                            "type": "Link",
                            "linkType": "Space",
                            "id": "xanbi6q061ft"
                          }
                        },
                        "id": "3hEosxIoaQdh3d2DXcs4CM",
                        "type": "Entry",
                        "createdAt": "2021-03-04T08:01:35.856Z",
                        "updatedAt": "2021-03-04T08:01:35.856Z",
                        "environment": {
                          "sys": {
                            "id": "stg",
                            "type": "Link",
                            "linkType": "Environment"
                          }
                        },
                        "revision": 1,
                        "contentType": {
                          "sys": {
                            "type": "Link",
                            "linkType": "ContentType",
                            "id": "navigationLink"
                          }
                        },
                        "locale": "en-US"
                      },
                      "fields": {
                        "title": "Narrow",
                        "url": "/narrow"
                      }
                    },
                    {
                      "sys": {
                        "space": {
                          "sys": {
                            "type": "Link",
                            "linkType": "Space",
                            "id": "xanbi6q061ft"
                          }
                        },
                        "id": "7nMd1w4F8f3wIDPKp21uvH",
                        "type": "Entry",
                        "createdAt": "2021-03-04T08:01:51.331Z",
                        "updatedAt": "2021-03-04T08:01:51.331Z",
                        "environment": {
                          "sys": {
                            "id": "stg",
                            "type": "Link",
                            "linkType": "Environment"
                          }
                        },
                        "revision": 1,
                        "contentType": {
                          "sys": {
                            "type": "Link",
                            "linkType": "ContentType",
                            "id": "navigationLink"
                          }
                        },
                        "locale": "en-US"
                      },
                      "fields": {
                        "title": "Trail",
                        "url": "/trail"
                      }
                    }
                  ],
                  "subCategoryUrl": "/running-shoes"
                }
              },
              {
                "sys": {
                  "space": {
                    "sys": {
                      "type": "Link",
                      "linkType": "Space",
                      "id": "xanbi6q061ft"
                    }
                  },
                  "id": "26zDPsgn53DgAU2iyKhCWm",
                  "type": "Entry",
                  "createdAt": "2021-03-04T08:04:57.588Z",
                  "updatedAt": "2021-03-04T08:04:57.588Z",
                  "environment": {
                    "sys": {
                      "id": "stg",
                      "type": "Link",
                      "linkType": "Environment"
                    }
                  },
                  "revision": 1,
                  "contentType": {
                    "sys": {
                      "type": "Link",
                      "linkType": "ContentType",
                      "id": "menuItemSubCategory"
                    }
                  },
                  "locale": "en-US"
                },
                "fields": {
                  "title": "Other Shoes",
                  "subCategoryLinks": [
                    {
                      "sys": {
                        "space": {
                          "sys": {
                            "type": "Link",
                            "linkType": "Space",
                            "id": "xanbi6q061ft"
                          }
                        },
                        "id": "1ftAf7znh0IJ0A5W2De1o5",
                        "type": "Entry",
                        "createdAt": "2021-03-04T08:02:31.521Z",
                        "updatedAt": "2021-03-04T08:02:31.521Z",
                        "environment": {
                          "sys": {
                            "id": "stg",
                            "type": "Link",
                            "linkType": "Environment"
                          }
                        },
                        "revision": 1,
                        "contentType": {
                          "sys": {
                            "type": "Link",
                            "linkType": "ContentType",
                            "id": "navigationLink"
                          }
                        },
                        "locale": "en-US"
                      },
                      "fields": {
                        "title": "Hiking",
                        "url": "/hiking"
                      }
                    },
                    {
                      "sys": {
                        "space": {
                          "sys": {
                            "type": "Link",
                            "linkType": "Space",
                            "id": "xanbi6q061ft"
                          }
                        },
                        "id": "1SgjxOCtP0DBdidGuO0iJE",
                        "type": "Entry",
                        "createdAt": "2021-03-04T08:02:52.519Z",
                        "updatedAt": "2021-03-04T08:02:52.519Z",
                        "environment": {
                          "sys": {
                            "id": "stg",
                            "type": "Link",
                            "linkType": "Environment"
                          }
                        },
                        "revision": 1,
                        "contentType": {
                          "sys": {
                            "type": "Link",
                            "linkType": "ContentType",
                            "id": "navigationLink"
                          }
                        },
                        "locale": "en-US"
                      },
                      "fields": {
                        "title": "Walking",
                        "url": "/walking"
                      }
                    },
                    {
                      "sys": {
                        "space": {
                          "sys": {
                            "type": "Link",
                            "linkType": "Space",
                            "id": "xanbi6q061ft"
                          }
                        },
                        "id": "4e1EFKesoqqudYRTJiKcb2",
                        "type": "Entry",
                        "createdAt": "2021-03-04T08:03:15.591Z",
                        "updatedAt": "2021-03-04T08:03:15.591Z",
                        "environment": {
                          "sys": {
                            "id": "stg",
                            "type": "Link",
                            "linkType": "Environment"
                          }
                        },
                        "revision": 1,
                        "contentType": {
                          "sys": {
                            "type": "Link",
                            "linkType": "ContentType",
                            "id": "navigationLink"
                          }
                        },
                        "locale": "en-US"
                      },
                      "fields": {
                        "title": "Sandals",
                        "url": "/sandals"
                      }
                    }
                  ]
                }
              }
            ],
            "categoryLinks": [
              {
                "sys": {
                  "space": {
                    "sys": {
                      "type": "Link",
                      "linkType": "Space",
                      "id": "xanbi6q061ft"
                    }
                  },
                  "id": "7DCLeVer1LXzccNotuuYpf",
                  "type": "Entry",
                  "createdAt": "2021-03-04T08:03:53.318Z",
                  "updatedAt": "2021-03-04T08:03:53.318Z",
                  "environment": {
                    "sys": {
                      "id": "stg",
                      "type": "Link",
                      "linkType": "Environment"
                    }
                  },
                  "revision": 1,
                  "contentType": {
                    "sys": {
                      "type": "Link",
                      "linkType": "ContentType",
                      "id": "navigationLink"
                    }
                  },
                  "locale": "en-US"
                },
                "fields": {
                  "title": "VIP Shoe Calendar",
                  "url": "/vip-shoe-calendar"
                }
              },
              {
                "sys": {
                  "space": {
                    "sys": {
                      "type": "Link",
                      "linkType": "Space",
                      "id": "xanbi6q061ft"
                    }
                  },
                  "id": "3pvVcAGiGrKtUsFzfk881n",
                  "type": "Entry",
                  "createdAt": "2021-03-04T08:04:29.168Z",
                  "updatedAt": "2021-03-04T08:04:29.168Z",
                  "environment": {
                    "sys": {
                      "id": "stg",
                      "type": "Link",
                      "linkType": "Environment"
                    }
                  },
                  "revision": 1,
                  "contentType": {
                    "sys": {
                      "type": "Link",
                      "linkType": "ContentType",
                      "id": "navigationLink"
                    }
                  },
                  "locale": "en-US"
                },
                "fields": {
                  "title": "Endangered Footwear",
                  "url": "/endangered-footwear"
                }
              }
            ]
          }
        },
        {
          "sys": {
            "space": {
              "sys": {
                "type": "Link",
                "linkType": "Space",
                "id": "xanbi6q061ft"
              }
            },
            "id": "4EikPGNUftENUz1HGtTyqN",
            "type": "Entry",
            "createdAt": "2021-03-04T08:08:20.228Z",
            "updatedAt": "2021-03-04T08:08:20.228Z",
            "environment": {
              "sys": {
                "id": "stg",
                "type": "Link",
                "linkType": "Environment"
              }
            },
            "revision": 1,
            "contentType": {
              "sys": {
                "type": "Link",
                "linkType": "ContentType",
                "id": "menuItemCategory"
              }
            },
            "locale": "en-US"
          },
          "fields": {
            "title": "Apparel",
            "subCategories": [
              {
                "sys": {
                  "space": {
                    "sys": {
                      "type": "Link",
                      "linkType": "Space",
                      "id": "xanbi6q061ft"
                    }
                  },
                  "id": "RdXyCPjHOt4ybr9p0O72l",
                  "type": "Entry",
                  "createdAt": "2021-03-04T08:06:52.369Z",
                  "updatedAt": "2021-03-04T08:06:52.369Z",
                  "environment": {
                    "sys": {
                      "id": "stg",
                      "type": "Link",
                      "linkType": "Environment"
                    }
                  },
                  "revision": 1,
                  "contentType": {
                    "sys": {
                      "type": "Link",
                      "linkType": "ContentType",
                      "id": "menuItemSubCategory"
                    }
                  },
                  "locale": "en-US"
                },
                "fields": {
                  "title": "Korsa",
                  "subCategoryLinks": [
                    {
                      "sys": {
                        "space": {
                          "sys": {
                            "type": "Link",
                            "linkType": "Space",
                            "id": "xanbi6q061ft"
                          }
                        },
                        "id": "24pMrhLXYRRH3vjhf1D0wO",
                        "type": "Entry",
                        "createdAt": "2021-03-04T08:06:10.094Z",
                        "updatedAt": "2021-03-04T08:06:10.094Z",
                        "environment": {
                          "sys": {
                            "id": "stg",
                            "type": "Link",
                            "linkType": "Environment"
                          }
                        },
                        "revision": 1,
                        "contentType": {
                          "sys": {
                            "type": "Link",
                            "linkType": "ContentType",
                            "id": "navigationLink"
                          }
                        },
                        "locale": "en-US"
                      },
                      "fields": {
                        "title": "Best Sellers",
                        "url": "/korsa-best-sellers"
                      }
                    },
                    {
                      "sys": {
                        "space": {
                          "sys": {
                            "type": "Link",
                            "linkType": "Space",
                            "id": "xanbi6q061ft"
                          }
                        },
                        "id": "yqY2RM4mpxCkk1G5Xer3l",
                        "type": "Entry",
                        "createdAt": "2021-03-04T08:06:38.212Z",
                        "updatedAt": "2021-03-04T08:06:38.212Z",
                        "environment": {
                          "sys": {
                            "id": "stg",
                            "type": "Link",
                            "linkType": "Environment"
                          }
                        },
                        "revision": 1,
                        "contentType": {
                          "sys": {
                            "type": "Link",
                            "linkType": "ContentType",
                            "id": "navigationLink"
                          }
                        },
                        "locale": "en-US"
                      },
                      "fields": {
                        "title": "New & Trending",
                        "url": "/korsa-trending"
                      }
                    }
                  ],
                  "subCategoryUrl": "/korsa"
                }
              },
              {
                "sys": {
                  "space": {
                    "sys": {
                      "type": "Link",
                      "linkType": "Space",
                      "id": "xanbi6q061ft"
                    }
                  },
                  "id": "41w2GhNAjtJ20tUVzLwAXI",
                  "type": "Entry",
                  "createdAt": "2021-03-04T08:07:45.929Z",
                  "updatedAt": "2021-03-04T08:07:45.929Z",
                  "environment": {
                    "sys": {
                      "id": "stg",
                      "type": "Link",
                      "linkType": "Environment"
                    }
                  },
                  "revision": 1,
                  "contentType": {
                    "sys": {
                      "type": "Link",
                      "linkType": "ContentType",
                      "id": "menuItemSubCategory"
                    }
                  },
                  "locale": "en-US"
                },
                "fields": {
                  "title": "Outwear",
                  "subCategoryLinks": [
                    {
                      "sys": {
                        "space": {
                          "sys": {
                            "type": "Link",
                            "linkType": "Space",
                            "id": "xanbi6q061ft"
                          }
                        },
                        "id": "1qsJBbGUQ796lhwlrX3b7K",
                        "type": "Entry",
                        "createdAt": "2021-03-04T08:07:23.392Z",
                        "updatedAt": "2021-03-04T08:07:23.392Z",
                        "environment": {
                          "sys": {
                            "id": "stg",
                            "type": "Link",
                            "linkType": "Environment"
                          }
                        },
                        "revision": 1,
                        "contentType": {
                          "sys": {
                            "type": "Link",
                            "linkType": "ContentType",
                            "id": "navigationLink"
                          }
                        },
                        "locale": "en-US"
                      },
                      "fields": {
                        "title": "Jackets",
                        "url": "/jackets"
                      }
                    },
                    {
                      "sys": {
                        "space": {
                          "sys": {
                            "type": "Link",
                            "linkType": "Space",
                            "id": "xanbi6q061ft"
                          }
                        },
                        "id": "3ftDK1oIJxdpMCrCGQoxXX",
                        "type": "Entry",
                        "createdAt": "2021-03-04T08:07:39.965Z",
                        "updatedAt": "2021-03-04T08:07:39.965Z",
                        "environment": {
                          "sys": {
                            "id": "stg",
                            "type": "Link",
                            "linkType": "Environment"
                          }
                        },
                        "revision": 1,
                        "contentType": {
                          "sys": {
                            "type": "Link",
                            "linkType": "ContentType",
                            "id": "navigationLink"
                          }
                        },
                        "locale": "en-US"
                      },
                      "fields": {
                        "title": "Vests",
                        "url": "/vests"
                      }
                    }
                  ]
                }
              }
            ],
            "categoryLinks": [
              {
                "sys": {
                  "space": {
                    "sys": {
                      "type": "Link",
                      "linkType": "Space",
                      "id": "xanbi6q061ft"
                    }
                  },
                  "id": "NW4FJ4py5NpKYgbqV5PRL",
                  "type": "Entry",
                  "createdAt": "2021-03-04T08:08:11.536Z",
                  "updatedAt": "2021-03-04T08:08:11.536Z",
                  "environment": {
                    "sys": {
                      "id": "stg",
                      "type": "Link",
                      "linkType": "Environment"
                    }
                  },
                  "revision": 1,
                  "contentType": {
                    "sys": {
                      "type": "Link",
                      "linkType": "ContentType",
                      "id": "navigationLink"
                    }
                  },
                  "locale": "en-US"
                },
                "fields": {
                  "title": "Outlet Apparel",
                  "url": "/outlet-apparel"
                }
              }
            ]
          }
        }
      ],
      "featuredPromotions": [
        {
          "sys": {
            "space": {
              "sys": {
                "type": "Link",
                "linkType": "Space",
                "id": "xanbi6q061ft"
              }
            },
            "id": "5xTq7ij0vCpDf4qpmQjH0g",
            "type": "Entry",
            "createdAt": "2021-03-04T08:11:25.247Z",
            "updatedAt": "2021-03-04T08:11:25.247Z",
            "environment": {
              "sys": {
                "id": "stg",
                "type": "Link",
                "linkType": "Environment"
              }
            },
            "revision": 1,
            "contentType": {
              "sys": {
                "type": "Link",
                "linkType": "ContentType",
                "id": "promotion"
              }
            },
            "locale": "en-US"
          },
          "fields": {
            "title": "Featured Korsa",
            "caption": "Featured Korsa",
            "image": {
              "sys": {
                "space": {
                  "sys": {
                    "type": "Link",
                    "linkType": "Space",
                    "id": "xanbi6q061ft"
                  }
                },
                "id": "1bnZUOs8uCIi74DJl46fwL",
                "type": "Entry",
                "createdAt": "2021-03-04T08:11:09.804Z",
                "updatedAt": "2021-03-04T08:11:09.804Z",
                "environment": {
                  "sys": {
                    "id": "stg",
                    "type": "Link",
                    "linkType": "Environment"
                  }
                },
                "revision": 1,
                "contentType": {
                  "sys": {
                    "type": "Link",
                    "linkType": "ContentType",
                    "id": "rrsImage"
                  }
                },
                "locale": "en-US"
              },
              "fields": {
                "title": "Featured Korsa",
                "image": {
                  "sys": {
                    "space": {
                      "sys": {
                        "type": "Link",
                        "linkType": "Space",
                        "id": "xanbi6q061ft"
                      }
                    },
                    "id": "7B2aNERKuA1D7UXYBWrz89",
                    "type": "Asset",
                    "createdAt": "2021-03-04T08:11:01.457Z",
                    "updatedAt": "2021-03-04T08:11:01.458Z",
                    "environment": {
                      "sys": {
                        "id": "stg",
                        "type": "Link",
                        "linkType": "Environment"
                      }
                    },
                    "revision": 1,
                    "locale": "en-US"
                  },
                  "fields": {
                    "title": "Korsa",
                    "description": "Image for Featured Korsa",
                    "file": {
                      "url": "//images.ctfassets.net/xanbi6q061ft/7B2aNERKuA1D7UXYBWrz89/04f4b2a0303c1368c8cba849d14f6711/14.png",
                      "details": {
                        "size": 137848,
                        "image": {
                          "width": 259,
                          "height": 319
                        }
                      },
                      "fileName": "14.png",
                      "contentType": "image/png"
                    }
                  }
                }
              }
            },
            "url": "/featured-korsa"
          }
        }
      ]
    }
  },
  {
    "sys": {
      "space": {
        "sys": {
          "type": "Link",
          "linkType": "Space",
          "id": "xanbi6q061ft"
        }
      },
      "id": "7jRw0LuWyOOZtRCv8SxXHu",
      "type": "Entry",
      "createdAt": "2021-03-04T08:11:51.870Z",
      "updatedAt": "2021-03-04T08:11:51.870Z",
      "environment": {
        "sys": {
          "id": "stg",
          "type": "Link",
          "linkType": "Environment"
        }
      },
      "revision": 1,
      "contentType": {
        "sys": {
          "type": "Link",
          "linkType": "ContentType",
          "id": "menuItem"
        }
      },
      "locale": "en-US"
    },
    "fields": {
      "title": "Men"
    }
  },
  {
    "sys": {
      "space": {
        "sys": {
          "type": "Link",
          "linkType": "Space",
          "id": "xanbi6q061ft"
        }
      },
      "id": "4op8hBn8PqGYcuEL1bKqvU",
      "type": "Entry",
      "createdAt": "2021-03-04T08:12:05.302Z",
      "updatedAt": "2021-03-04T08:12:05.302Z",
      "environment": {
        "sys": {
          "id": "stg",
          "type": "Link",
          "linkType": "Environment"
        }
      },
      "revision": 1,
      "contentType": {
        "sys": {
          "type": "Link",
          "linkType": "ContentType",
          "id": "menuItem"
        }
      },
      "locale": "en-US"
    },
    "fields": {
      "title": "Kids"
    }
  },
  {
    "sys": {
      "space": {
        "sys": {
          "type": "Link",
          "linkType": "Space",
          "id": "xanbi6q061ft"
        }
      },
      "id": "2QGLi9kuVmxqwjTPrnogwy",
      "type": "Entry",
      "createdAt": "2021-03-04T08:12:18.050Z",
      "updatedAt": "2021-03-04T08:12:18.050Z",
      "environment": {
        "sys": {
          "id": "stg",
          "type": "Link",
          "linkType": "Environment"
        }
      },
      "revision": 1,
      "contentType": {
        "sys": {
          "type": "Link",
          "linkType": "ContentType",
          "id": "menuItem"
        }
      },
      "locale": "en-US"
    },
    "fields": {
      "title": "Gear"
    }
  },
  {
    "sys": {
      "space": {
        "sys": {
          "type": "Link",
          "linkType": "Space",
          "id": "xanbi6q061ft"
        }
      },
      "id": "1wzqQSCDFd2W48CkwMjKnI",
      "type": "Entry",
      "createdAt": "2021-03-04T08:12:33.214Z",
      "updatedAt": "2021-03-04T08:12:33.214Z",
      "environment": {
        "sys": {
          "id": "stg",
          "type": "Link",
          "linkType": "Environment"
        }
      },
      "revision": 1,
      "contentType": {
        "sys": {
          "type": "Link",
          "linkType": "ContentType",
          "id": "menuItem"
        }
      },
      "locale": "en-US"
    },
    "fields": {
      "title": "Outlet"
    }
  },
  {
    "sys": {
      "space": {
        "sys": {
          "type": "Link",
          "linkType": "Space",
          "id": "xanbi6q061ft"
        }
      },
      "id": "1XGi1vIPszvPHpxil6fyZv",
      "type": "Entry",
      "createdAt": "2021-03-04T08:12:48.303Z",
      "updatedAt": "2021-03-04T08:12:48.303Z",
      "environment": {
        "sys": {
          "id": "stg",
          "type": "Link",
          "linkType": "Environment"
        }
      },
      "revision": 1,
      "contentType": {
        "sys": {
          "type": "Link",
          "linkType": "ContentType",
          "id": "menuItem"
        }
      },
      "locale": "en-US"
    },
    "fields": {
      "title": "Fit Finder"
    }
  }
]
